odoo/addons/mrp_bom_produce_delay/README.rst
odoo/addons/mrp_bom_produce_delay/__init__.py
odoo/addons/mrp_bom_produce_delay/__manifest__.py
odoo/addons/mrp_bom_produce_delay/i18n/fr.po
odoo/addons/mrp_bom_produce_delay/i18n/it.po
odoo/addons/mrp_bom_produce_delay/i18n/mrp_bom_produce_delay.pot
odoo/addons/mrp_bom_produce_delay/model/__init__.py
odoo/addons/mrp_bom_produce_delay/model/mrp_bom.py
odoo/addons/mrp_bom_produce_delay/readme/CONTRIBUTORS.rst
odoo/addons/mrp_bom_produce_delay/readme/DESCRIPTION.rst
odoo/addons/mrp_bom_produce_delay/static/description/icon.png
odoo/addons/mrp_bom_produce_delay/static/description/index.html
odoo/addons/mrp_bom_produce_delay/static/description/mrp_bom_produce_delay.png
odoo/addons/mrp_bom_produce_delay/tests/__init__.py
odoo/addons/mrp_bom_produce_delay/tests/test_bom_produce_delay.py
odoo/addons/mrp_bom_produce_delay/view/mrp_bom.xml
odoo_addon_mrp_bom_produce_delay-16.0.1.0.0.5.dist-info/METADATA
odoo_addon_mrp_bom_produce_delay-16.0.1.0.0.5.dist-info/WHEEL
odoo_addon_mrp_bom_produce_delay-16.0.1.0.0.5.dist-info/top_level.txt
odoo_addon_mrp_bom_produce_delay-16.0.1.0.0.5.dist-info/RECORD
