Metadata-Version: 2.1
Name: odoo-addon-mrp_bom_produce_delay
Version: 16.0.1.0.0.5
Summary: Add Product Delay in BoM, linked to Product Produce Delay.
Home-page: https://github.com/OCA/manufacture
Author: GRAP, Odoo Community Association (OCA)
Author-email: support@odoo-community.org
License: AGPL-3
Classifier: Programming Language :: Python
Classifier: Framework :: Odoo
Classifier: Framework :: Odoo :: 16.0
Classifier: License :: OSI Approved :: GNU Affero General Public License v3
Requires-Python: >=3.10
Requires-Dist: odoo<16.1dev,>=16.0a
